statbank/__init__.py
statbank/config.py
statbank/error.py
statbank/request.py
statbank/resources.py
statbank/time.py
statbank/url.py
tests/__init__.py
tests/test_service.py
tests/test_time.py
tests/test_url.py
statbank-1.0.1.dist-info/LICENSE
statbank-1.0.1.dist-info/METADATA
statbank-1.0.1.dist-info/WHEEL
statbank-1.0.1.dist-info/top_level.txt
statbank-1.0.1.dist-info/RECORD
