Metadata-Version: 2.1
Name: statbank
Version: 1.0.1
Summary: Statbank API client library
Home-page: https://github.com/bytesandbrains/statbank-python
Author: Bytes & Brains
Author-email: developers@bytesandbrains.com
License: MIT
Platform: UNKNOWN
License-File: LICENSE
Requires-Dist: python-dateutil
